{
  "page": {
    "title": "Právní informace",
    "subtitle": "DVSG Ostrava-Poruba"
  },
  "sections": {
    "identification": {
      "title": "Identifikační údaje",
      "company_info": {
        "name": "Družstvo pro výstavbu a správu garáží Ostrava-Poruba",
        "address": "Bohuslava Martinů 3/6090",
        "city": "708 00 Ostrava-Poruba",
        "ico": "41033558",
        "registry": "Krajský soud v Ostravě",
        "bank_account": "1646763319/0800",
        "bank_name": "Česká spořitelna, a.s."
      }
    },
    "contact": {
      "title": "Kontaktní údaje",
      "details": {
        "phone": "776 230 108",
        "email": "info@dvsg.cz",
        "office_hours": "Každou třetí pracovní středu v měsíci od 16:30 do 17:30 hodin v kanceláři družstva"
      }
    },
    "activities": {
      "title": "Předmět činnosti",
      "description": "Družstvo poskytuje služby výhradně svým členům v oblasti:",
      "items": [
        "Správy garážových objektů pro členy družstva",
        "Pronájmu garážových stání členům družstva",
        "Údržby a oprav garážových objektů",
        "Administrativní činnosti související se správou garáží"
      ]
    },
    "legal_framework": {
      "title": "Právní předpisy",
      "description": "Činnost družstva se řídí zejména:",
      "items": [
        "Zákonem č. 90/2012 Sb., o obchodních společnostech a družstvech",
        "Občanským zákoníkem č. 89/2012 Sb.",
        "Stanovami družstva"
      ]
    },
    "public_documents": {
      "title": "Veřejně dostupné dokumenty",
      "description": "Následující dokumenty jsou veřejně dostupné v obchodním rejstříku na justice.cz:",
      "registry_url": "https://or.justice.cz/ias/ui/rejstrik-firma.vysledky?subjektId=215526&typ=UPLNY",
      "collection_url": "https://or.justice.cz/ias/ui/vypis-sl-firma?subjektId=215526",
      "items": [
        "Stanovy družstva",
        "Účetní závěrka za posledních 5 let",
        "Výroční zpráva",
        "Složení orgánů družstva"
      ]
    },
    "member_info": {
      "title": "Informace pro členy",
      "heading": "Informace pro členy",
      "text": "Podrobné informace, dokumenty a usnesení určené pro členy družstva jsou k dispozici během úředních hodin v kanceláři družstva nebo na vyžádání na e-mailu info@dvsg.cz."
    }
  }
}
